[
    {
        "Judul Buku": "The Psychology of Money",
        "Nama Pengarang": "Morgan Housel",
        "Tahun Terbit": "8 September 2020"
    },
    {
        "Judul Buku": "Filosofi Teras",
        "Nama Pengarang": "Henry Manampiring",
        "Tahun Terbit": "26 November 2018"
    },
    {
        "Judul Buku": "Atomic Habits",
        "Nama Pengarang": "James Clear",
        "Tahun Terbit": "16 Oktober 2018"
    },
    {
        "Judul Buku": "Goodbye, Things",
        "Nama Pengarang": "Fumio Sasaki",
        "Tahun Terbit": "19 November 2018"
    }
]